{
  "Constituency Number": 12,
  "constituency_name": "GADCHIROLI-CHIMUR (ST) PARLIAMENTARY",
  "Total Number of Electors": 245248,
  "serial_no_wise_details": [
    {
      "Serial No. Of Polling Station": 1,
      "Total Number of valid votes": 857,
      "Number of Rejected votes": 0,
      "NOTA": 12,
      "Total": 869,
      "candidate_votes": [
        216,
        601,
        9,
        1,
        1,
        2,
        20,
        1,
        1,
        5
      ]
    },
    {
      "Serial No. Of Polling Station": 2,
      "Total Number of valid votes": 618,
      "Number of Rejected votes": 0,
      "NOTA": 14,
      "Total": 632,
      "candidate_votes": [
        377,
        214,
        5,
        2,
        4,
        1,
        9,
        0,
        2,
        4
      ]
    },
    {
      "Serial No. Of Polling Station": 3,
      "Total Number of valid votes": 424,
      "Number of Rejected votes": 0,
      "NOTA": 9,
      "Total": 433,
      "candidate_votes": [
        82,
        331,
        1,
        0,
        1,
        1,
        1,
        0,
        2,
        5
      ]
    },
    {
      "Serial No. Of Polling Station": 4,
      "Total Number of valid votes": 732,
      "Number of Rejected votes": 0,
      "NOTA": 0,
      "Total": 732,
      "candidate_votes": [
        593,
        132,
        1,
        1,
        1,
        2,
        1,
        0,
        0,
        1
      ]
    },
    {
      "Serial No. Of Polling Station": 5,
      "Total Number of valid votes": 520,
      "Number of Rejected votes": 0,
      "NOTA": 2,
      "Total": 522,
      "candidate_votes": [
        462,
        56,
        2,
        0,
        0,
        0,
        0,
        0,
        0,
        0
      ]
    },
    {
      "Serial No. Of Polling Station": 6,
      "Total Number of valid votes": 485,
      "Number of Rejected votes": 0,
      "NOTA": 3,
      "Total": 488,
      "candidate_votes": [
        438,
        46,
        0,
        0,
        0,
        0,
        0,
        0,
        1,
        0
      ]
    },
    {
      "Serial No. Of Polling Station": 7,
      "Total Number of valid votes": 397,
      "Number of Rejected votes": 0,
      "NOTA": 0,
      "Total": 397,
      "candidate_votes": [
        304,
        92,
        0,
        0,
        0,
        0,
        0,
        0,
        1,
        0
      ]
    },
    {
      "Serial No. Of Polling Station": 8,
      "Total Number of valid votes": 437,
      "Number of Rejected votes": 0,
      "NOTA": 18,
      "Total": 455,
      "candidate_votes": [
        86,
        330,
        8,
        1,
        2,
        0,
        0,
        1,
        4,
        5
      ]
    },
    {
      "Serial No. Of Polling Station": 9,
      "Total Number of valid votes": 858,
      "Number of Rejected votes": 0,
      "NOTA": 15,
      "Total": 873,
      "candidate_votes": [
        180,
        625,
        10,
        6,
        3,
        7,
        8,
        4,
        6,
        9
      ]
    },
    {
      "Serial No. Of Polling Station": 10,
      "Total Number of valid votes": 277,
      "Number of Rejected votes": 0,
      "NOTA": 33,
      "Total": 310,
      "candidate_votes": [
        50,
        197,
        5,
        2,
        3,
        0,
        3,
        1,
        5,
        11
      ]
    },
    {
      "Serial No. Of Polling Station": 11,
      "Total Number of valid votes": 675,
      "Number of Rejected votes": 0,
      "NOTA": 32,
      "Total": 707,
      "candidate_votes": [
        185,
        382,
        26,
        8,
        8,
        5,
        8,
        4,
        17,
        32
      ]
    },
    {
      "Serial No. Of Polling Station": 12,
      "Total Number of valid votes": 285,
      "Number of Rejected votes": 0,
      "NOTA": 23,
      "Total": 308,
      "candidate_votes": [
        30,
        222,
        7,
        3,
        2,
        0,
        4,
        2,
        4,
        11
      ]
    },
    {
      "Serial No. Of Polling Station": 13,
      "Total Number of valid votes": 451,
      "Number of Rejected votes": 0,
      "NOTA": 50,
      "Total": 501,
      "candidate_votes": [
        36,
        354,
        14,
        5,
        1,
        2,
        6,
        10,
        13,
        10
      ]
    },
    {
      "Serial No. Of Polling Station": 14,
      "Total Number of valid votes": 555,
      "Number of Rejected votes": 0,
      "NOTA": 25,
      "Total": 580,
      "candidate_votes": [
        81,
        419,
        17,
        9,
        3,
        4,
        0,
        6,
        5,
        11
      ]
    },
    {
      "Serial No. Of Polling Station": 15,
      "Total Number of valid votes": 621,
      "Number of Rejected votes": 0,
      "NOTA": 19,
      "Total": 640,
      "candidate_votes": [
        202,
        347,
        10,
        4,
        4,
        7,
        6,
        8,
        17,
        16
      ]
    },
    {
      "Serial No. Of Polling Station": 16,
      "Total Number of valid votes": 631,
      "Number of Rejected votes": 0,
      "NOTA": 9,
      "Total": 640,
      "candidate_votes": [
        324,
        290,
        7,
        1,
        0,
        4,
        1,
        3,
        0,
        1
      ]
    },
    {
      "Serial No. Of Polling Station": 17,
      "Total Number of valid votes": 332,
      "Number of Rejected votes": 0,
      "NOTA": 8,
      "Total": 340,
      "candidate_votes": [
        81,
        230,
        6,
        0,
        0,
        2,
        1,
        5,
        3,
        4
      ]
    },
    {
      "Serial No. Of Polling Station": 18,
      "Total Number of valid votes": 414,
      "Number of Rejected votes": 0,
      "NOTA": 6,
      "Total": 420,
      "candidate_votes": [
        215,
        183,
        2,
        1,
        2,
        2,
        2,
        2,
        4,
        1
      ]
    },
    {
      "Serial No. Of Polling Station": 19,
      "Total Number of valid votes": 573,
      "Number of Rejected votes": 0,
      "NOTA": 20,
      "Total": 593,
      "candidate_votes": [
        156,
        383,
        9,
        6,
        4,
        2,
        2,
        2,
        3,
        6
      ]
    },
    {
      "Serial No. Of Polling Station": 20,
      "Total Number of valid votes": 176,
      "Number of Rejected votes": 0,
      "NOTA": 7,
      "Total": 183,
      "candidate_votes": [
        14,
        145,
        8,
        2,
        0,
        0,
        1,
        2,
        2,
        2
      ]
    },
    {
      "Serial No. Of Polling Station": 21,
      "Total Number of valid votes": 490,
      "Number of Rejected votes": 0,
      "NOTA": 33,
      "Total": 523,
      "candidate_votes": [
        185,
        255,
        7,
        4,
        3,
        8,
        3,
        3,
        8,
        14
      ]
    },
    {
      "Serial No. Of Polling Station": 22,
      "Total Number of valid votes": 288,
      "Number of Rejected votes": 0,
      "NOTA": 67,
      "Total": 355,
      "candidate_votes": [
        43,
        163,
        12,
        6,
        1,
        7,
        5,
        8,
        10,
        33
      ]
    },
    {
      "Serial No. Of Polling Station": 23,
      "Total Number of valid votes": 505,
      "Number of Rejected votes": 0,
      "NOTA": 16,
      "Total": 521,
      "candidate_votes": [
        45,
        394,
        21,
        9,
        4,
        2,
        6,
        2,
        7,
        15
      ]
    },
    {
      "Serial No. Of Polling Station": 24,
      "Total Number of valid votes": 497,
      "Number of Rejected votes": 0,
      "NOTA": 21,
      "Total": 518,
      "candidate_votes": [
        177,
        283,
        14,
        1,
        0,
        4,
        3,
        1,
        7,
        7
      ]
    },
    {
      "Serial No. Of Polling Station": 25,
      "Total Number of valid votes": 380,
      "Number of Rejected votes": 0,
      "NOTA": 13,
      "Total": 393,
      "candidate_votes": [
        147,
        213,
        1,
        6,
        0,
        2,
        3,
        0,
        5,
        3
      ]
    },
    {
      "Serial No. Of Polling Station": 26,
      "Total Number of valid votes": 536,
      "Number of Rejected votes": 0,
      "NOTA": 16,
      "Total": 552,
      "candidate_votes": [
        56,
        435,
        20,
        3,
        2,
        1,
        1,
        8,
        6,
        4
      ]
    },
    {
      "Serial No. Of Polling Station": 27,
      "Total Number of valid votes": 698,
      "Number of Rejected votes": 0,
      "NOTA": 16,
      "Total": 714,
      "candidate_votes": [
        371,
        273,
        15,
        4,
        4,
        2,
        4,
        5,
        11,
        9
      ]
    },
    {
      "Serial No. Of Polling Station": 28,
      "Total Number of valid votes": 656,
      "Number of Rejected votes": 0,
      "NOTA": 20,
      "Total": 676,
      "candidate_votes": [
        274,
        321,
        13,
        6,
        5,
        8,
        3,
        7,
        8,
        11
      ]
    },
    {
      "Serial No. Of Polling Station": 29,
      "Total Number of valid votes": 705,
      "Number of Rejected votes": 0,
      "NOTA": 4,
      "Total": 709,
      "candidate_votes": [
        490,
        207,
        4,
        0,
        0,
        0,
        1,
        3,
        0,
        0
      ]
    },
    {
      "Serial No. Of Polling Station": 30,
      "Total Number of valid votes": 486,
      "Number of Rejected votes": 0,
      "NOTA": 4,
      "Total": 490,
      "candidate_votes": [
        334,
        148,
        2,
        0,
        0,
        0,
        1,
        0,
        0,
        1
      ]
    },
    {
      "Serial No. Of Polling Station": 31,
      "Total Number of valid votes": 809,
      "Number of Rejected votes": 0,
      "NOTA": 7,
      "Total": 816,
      "candidate_votes": [
        692,
        102,
        1,
        1,
        1,
        1,
        7,
        2,
        0,
        2
      ]
    },
    {
      "Serial No. Of Polling Station": 32,
      "Total Number of valid votes": 899,
      "Number of Rejected votes": 0,
      "NOTA": 6,
      "Total": 905,
      "candidate_votes": [
        832,
        62,
        1,
        0,
        0,
        1,
        1,
        1,
        0,
        1
      ]
    },
    {
      "Serial No. Of Polling Station": 33,
      "Total Number of valid votes": 708,
      "Number of Rejected votes": 0,
      "NOTA": 10,
      "Total": 718,
      "candidate_votes": [
        394,
        287,
        2,
        1,
        1,
        2,
        1,
        5,
        7,
        8
      ]
    },
    {
      "Serial No. Of Polling Station": 34,
      "Total Number of valid votes": 736,
      "Number of Rejected votes": 0,
      "NOTA": 10,
      "Total": 746,
      "candidate_votes": [
        105,
        601,
        11,
        2,
        1,
        2,
        4,
        2,
        2,
        6
      ]
    },
    {
      "Serial No. Of Polling Station": 35,
      "Total Number of valid votes": 907,
      "Number of Rejected votes": 0,
      "NOTA": 10,
      "Total": 917,
      "candidate_votes": [
        316,
        560,
        6,
        4,
        5,
        0,
        5,
        1,
        2,
        8
      ]
    },
    {
      "Serial No. Of Polling Station": 36,
      "Total Number of valid votes": 662,
      "Number of Rejected votes": 0,
      "NOTA": 3,
      "Total": 665,
      "candidate_votes": [
        543,
        108,
        8,
        0,
        0,
        0,
        1,
        0,
        1,
        1
      ]
    },
    {
      "Serial No. Of Polling Station": 37,
      "Total Number of valid votes": 560,
      "Number of Rejected votes": 0,
      "NOTA": 6,
      "Total": 566,
      "candidate_votes": [
        156,
        373,
        9,
        2,
        4,
        2,
        0,
        1,
        3,
        10
      ]
    },
    {
      "Serial No. Of Polling Station": 38,
      "Total Number of valid votes": 576,
      "Number of Rejected votes": 0,
      "NOTA": 12,
      "Total": 588,
      "candidate_votes": [
        197,
        332,
        6,
        2,
        0,
        1,
        24,
        0,
        8,
        6
      ]
    },
    {
      "Serial No. Of Polling Station": 39,
      "Total Number of valid votes": 753,
      "Number of Rejected votes": 0,
      "NOTA": 2,
      "Total": 755,
      "candidate_votes": [
        707,
        44,
        2,
        0,
        0,
        0,
        0,
        0,
        0,
        0
      ]
    },
    {
      "Serial No. Of Polling Station": 40,
      "Total Number of valid votes": 353,
      "Number of Rejected votes": 0,
      "NOTA": 6,
      "Total": 359,
      "candidate_votes": [
        192,
        149,
        2,
        2,
        0,
        0,
        3,
        0,
        0,
        5
      ]
    },
    {
      "Serial No. Of Polling Station": 41,
      "Total Number of valid votes": 621,
      "Number of Rejected votes": 0,
      "NOTA": 23,
      "Total": 644,
      "candidate_votes": [
        203,
        371,
        11,
        3,
        2,
        5,
        3,
        5,
        8,
        10
      ]
    },
    {
      "Serial No. Of Polling Station": 42,
      "Total Number of valid votes": 794,
      "Number of Rejected votes": 0,
      "NOTA": 12,
      "Total": 806,
      "candidate_votes": [
        275,
        491,
        8,
        2,
        1,
        3,
        1,
        3,
        3,
        7
      ]
    },
    {
      "Serial No. Of Polling Station": 43,
      "Total Number of valid votes": 577,
      "Number of Rejected votes": 0,
      "NOTA": 15,
      "Total": 592,
      "candidate_votes": [
        170,
        371,
        13,
        0,
        1,
        1,
        8,
        2,
        7,
        4
      ]
    },
    {
      "Serial No. Of Polling Station": 44,
      "Total Number of valid votes": 930,
      "Number of Rejected votes": 0,
      "NOTA": 7,
      "Total": 937,
      "candidate_votes": [
        715,
        203,
        3,
        0,
        1,
        0,
        2,
        2,
        3,
        1
      ]
    },
    {
      "Serial No. Of Polling Station": 45,
      "Total Number of valid votes": 818,
      "Number of Rejected votes": 0,
      "NOTA": 4,
      "Total": 822,
      "candidate_votes": [
        724,
        93,
        0,
        0,
        0,
        0,
        0,
        0,
        0,
        1
      ]
    },
    {
      "Serial No. Of Polling Station": 46,
      "Total Number of valid votes": 386,
      "Number of Rejected votes": 0,
      "NOTA": 8,
      "Total": 394,
      "candidate_votes": [
        220,
        156,
        2,
        0,
        0,
        2,
        0,
        2,
        3,
        1
      ]
    },
    {
      "Serial No. Of Polling Station": 47,
      "Total Number of valid votes": 771,
      "Number of Rejected votes": 0,
      "NOTA": 15,
      "Total": 786,
      "candidate_votes": [
        308,
        430,
        4,
        2,
        2,
        5,
        1,
        0,
        9,
        10
      ]
    },
    {
      "Serial No. Of Polling Station": 48,
      "Total Number of valid votes": 709,
      "Number of Rejected votes": 0,
      "NOTA": 6,
      "Total": 715,
      "candidate_votes": [
        441,
        251,
        4,
        3,
        2,
        2,
        1,
        1,
        1,
        3
      ]
    },
    {
      "Serial No. Of Polling Station": 49,
      "Total Number of valid votes": 699,
      "Number of Rejected votes": 0,
      "NOTA": 19,
      "Total": 718,
      "candidate_votes": [
        351,
        311,
        13,
        1,
        3,
        2,
        1,
        2,
        5,
        10
      ]
    },
    {
      "Serial No. Of Polling Station": 50,
      "Total Number of valid votes": 533,
      "Number of Rejected votes": 0,
      "NOTA": 11,
      "Total": 544,
      "candidate_votes": [
        366,
        148,
        3,
        0,
        1,
        1,
        0,
        3,
        6,
        5
      ]
    },
    {
      "Serial No. Of Polling Station": 51,
      "Total Number of valid votes": 823,
      "Number of Rejected votes": 0,
      "NOTA": 6,
      "Total": 829,
      "candidate_votes": [
        670,
        141,
        4,
        1,
        0,
        2,
        0,
        3,
        1,
        1
      ]
    },
    {
      "Serial No. Of Polling Station": 52,
      "Total Number of valid votes": 703,
      "Number of Rejected votes": 0,
      "NOTA": 15,
      "Total": 718,
      "candidate_votes": [
        453,
        224,
        9,
        0,
        2,
        1,
        2,
        2,
        5,
        5
      ]
    },
    {
      "Serial No. Of Polling Station": 53,
      "Total Number of valid votes": 960,
      "Number of Rejected votes": 0,
      "NOTA": 9,
      "Total": 969,
      "candidate_votes": [
        749,
        201,
        4,
        1,
        0,
        1,
        0,
        1,
        2,
        1
      ]
    },
    {
      "Serial No. Of Polling Station": 54,
      "Total Number of valid votes": 670,
      "Number of Rejected votes": 0,
      "NOTA": 1,
      "Total": 671,
      "candidate_votes": [
        554,
        107,
        2,
        0,
        1,
        1,
        0,
        0,
        2,
        3
      ]
    },
    {
      "Serial No. Of Polling Station": 55,
      "Total Number of valid votes": 482,
      "Number of Rejected votes": 0,
      "NOTA": 0,
      "Total": 482,
      "candidate_votes": [
        441,
        38,
        0,
        0,
        1,
        0,
        0,
        0,
        1,
        1
      ]
    },
    {
      "Serial No. Of Polling Station": 56,
      "Total Number of valid votes": 426,
      "Number of Rejected votes": 0,
      "NOTA": 10,
      "Total": 436,
      "candidate_votes": [
        315,
        101,
        2,
        1,
        0,
        0,
        0,
        2,
        1,
        4
      ]
    },
    {
      "Serial No. Of Polling Station": 57,
      "Total Number of valid votes": 708,
      "Number of Rejected votes": 0,
      "NOTA": 19,
      "Total": 727,
      "candidate_votes": [
        347,
        319,
        12,
        4,
        2,
        4,
        3,
        4,
        6,
        7
      ]
    },
    {
      "Serial No. Of Polling Station": 58,
      "Total Number of valid votes": 691,
      "Number of Rejected votes": 0,
      "NOTA": 13,
      "Total": 704,
      "candidate_votes": [
        192,
        461,
        12,
        0,
        1,
        2,
        4,
        8,
        3,
        8
      ]
    },
    {
      "Serial No. Of Polling Station": 59,
      "Total Number of valid votes": 381,
      "Number of Rejected votes": 0,
      "NOTA": 8,
      "Total": 389,
      "candidate_votes": [
        152,
        213,
        5,
        1,
        2,
        2,
        2,
        1,
        1,
        2
      ]
    },
    {
      "Serial No. Of Polling Station": 60,
      "Total Number of valid votes": 573,
      "Number of Rejected votes": 0,
      "NOTA": 1,
      "Total": 574,
      "candidate_votes": [
        403,
        167,
        0,
        0,
        1,
        0,
        0,
        0,
        0,
        2
      ]
    },
    {
      "Serial No. Of Polling Station": 61,
      "Total Number of valid votes": 602,
      "Number of Rejected votes": 0,
      "NOTA": 6,
      "Total": 608,
      "candidate_votes": [
        507,
        91,
        2,
        0,
        1,
        1,
        0,
        0,
        0,
        0
      ]
    },
    {
      "Serial No. Of Polling Station": 62,
      "Total Number of valid votes": 0,
      "Number of Rejected votes": 0,
      "NOTA": 0,
      "Total": 0,
      "candidate_votes": [
        0,
        0,
        0,
        0,
        0,
        0,
        0,
        0,
        0,
        0
      ]
    },
    {
      "Serial No. Of Polling Station": 63,
      "Total Number of valid votes": 591,
      "Number of Rejected votes": 0,
      "NOTA": 3,
      "Total": 594,
      "candidate_votes": [
        500,
        88,
        2,
        0,
        0,
        0,
        0,
        0,
        1,
        0
      ]
    },
    {
      "Serial No. Of Polling Station": 64,
      "Total Number of valid votes": 790,
      "Number of Rejected votes": 0,
      "NOTA": 19,
      "Total": 809,
      "candidate_votes": [
        109,
        619,
        34,
        4,
        0,
        4,
        4,
        5,
        5,
        6
      ]
    },
    {
      "Serial No. Of Polling Station": 65,
      "Total Number of valid votes": 288,
      "Number of Rejected votes": 0,
      "NOTA": 5,
      "Total": 293,
      "candidate_votes": [
        31,
        237,
        4,
        2,
        0,
        3,
        1,
        1,
        3,
        6
      ]
    },
    {
      "Serial No. Of Polling Station": 66,
      "Total Number of valid votes": 560,
      "Number of Rejected votes": 0,
      "NOTA": 13,
      "Total": 573,
      "candidate_votes": [
        105,
        425,
        8,
        3,
        1,
        2,
        4,
        1,
        5,
        6
      ]
    },
    {
      "Serial No. Of Polling Station": 67,
      "Total Number of valid votes": 512,
      "Number of Rejected votes": 0,
      "NOTA": 18,
      "Total": 530,
      "candidate_votes": [
        197,
        287,
        12,
        1,
        2,
        1,
        3,
        1,
        4,
        4
      ]
    },
    {
      "Serial No. Of Polling Station": 68,
      "Total Number of valid votes": 642,
      "Number of Rejected votes": 0,
      "NOTA": 30,
      "Total": 672,
      "candidate_votes": [
        314,
        263,
        13,
        2,
        4,
        3,
        6,
        10,
        11,
        16
      ]
    },
    {
      "Serial No. Of Polling Station": 69,
      "Total Number of valid votes": 644,
      "Number of Rejected votes": 0,
      "NOTA": 27,
      "Total": 671,
      "candidate_votes": [
        322,
        296,
        6,
        2,
        3,
        0,
        2,
        1,
        5,
        7
      ]
    },
    {
      "Serial No. Of Polling Station": 70,
      "Total Number of valid votes": 620,
      "Number of Rejected votes": 0,
      "NOTA": 48,
      "Total": 668,
      "candidate_votes": [
        223,
        356,
        4,
        1,
        4,
        3,
        1,
        7,
        12,
        9
      ]
    },
    {
      "Serial No. Of Polling Station": 71,
      "Total Number of valid votes": 596,
      "Number of Rejected votes": 0,
      "NOTA": 32,
      "Total": 628,
      "candidate_votes": [
        183,
        345,
        11,
        2,
        3,
        5,
        5,
        13,
        15,
        14
      ]
    },
    {
      "Serial No. Of Polling Station": 72,
      "Total Number of valid votes": 644,
      "Number of Rejected votes": 0,
      "NOTA": 41,
      "Total": 685,
      "candidate_votes": [
        312,
        271,
        19,
        2,
        4,
        4,
        5,
        4,
        11,
        12
      ]
    },
    {
      "Serial No. Of Polling Station": 73,
      "Total Number of valid votes": 481,
      "Number of Rejected votes": 0,
      "NOTA": 35,
      "Total": 516,
      "candidate_votes": [
        192,
        226,
        7,
        6,
        2,
        7,
        8,
        12,
        8,
        13
      ]
    },
    {
      "Serial No. Of Polling Station": 74,
      "Total Number of valid votes": 501,
      "Number of Rejected votes": 0,
      "NOTA": 57,
      "Total": 558,
      "candidate_votes": [
        237,
        204,
        6,
        2,
        4,
        4,
        8,
        11,
        9,
        16
      ]
    },
    {
      "Serial No. Of Polling Station": 75,
      "Total Number of valid votes": 639,
      "Number of Rejected votes": 0,
      "NOTA": 32,
      "Total": 671,
      "candidate_votes": [
        198,
        357,
        15,
        5,
        5,
        10,
        9,
        12,
        15,
        13
      ]
    },
    {
      "Serial No. Of Polling Station": 76,
      "Total Number of valid votes": 229,
      "Number of Rejected votes": 0,
      "NOTA": 12,
      "Total": 241,
      "candidate_votes": [
        30,
        175,
        6,
        3,
        1,
        1,
        3,
        5,
        2,
        3
      ]
    },
    {
      "Serial No. Of Polling Station": 77,
      "Total Number of valid votes": 347,
      "Number of Rejected votes": 0,
      "NOTA": 34,
      "Total": 381,
      "candidate_votes": [
        27,
        237,
        11,
        4,
        7,
        1,
        6,
        7,
        17,
        30
      ]
    },
    {
      "Serial No. Of Polling Station": 78,
      "Total Number of valid votes": 261,
      "Number of Rejected votes": 0,
      "NOTA": 23,
      "Total": 284,
      "candidate_votes": [
        33,
        181,
        12,
        4,
        2,
        5,
        5,
        2,
        7,
        10
      ]
    },
    {
      "Serial No. Of Polling Station": 79,
      "Total Number of valid votes": 382,
      "Number of Rejected votes": 0,
      "NOTA": 38,
      "Total": 420,
      "candidate_votes": [
        61,
        263,
        17,
        2,
        4,
        2,
        4,
        5,
        9,
        15
      ]
    },
    {
      "Serial No. Of Polling Station": 80,
      "Total Number of valid votes": 491,
      "Number of Rejected votes": 0,
      "NOTA": 49,
      "Total": 540,
      "candidate_votes": [
        80,
        337,
        17,
        3,
        2,
        5,
        4,
        9,
        11,
        23
      ]
    },
    {
      "Serial No. Of Polling Station": 81,
      "Total Number of valid votes": 327,
      "Number of Rejected votes": 0,
      "NOTA": 16,
      "Total": 343,
      "candidate_votes": [
        23,
        267,
        8,
        2,
        2,
        2,
        3,
        2,
        5,
        13
      ]
    },
    {
      "Serial No. Of Polling Station": 82,
      "Total Number of valid votes": 296,
      "Number of Rejected votes": 0,
      "NOTA": 27,
      "Total": 323,
      "candidate_votes": [
        90,
        162,
        9,
        1,
        4,
        4,
        4,
        7,
        6,
        9
      ]
    },
    {
      "Serial No. Of Polling Station": 83,
      "Total Number of valid votes": 432,
      "Number of Rejected votes": 0,
      "NOTA": 55,
      "Total": 487,
      "candidate_votes": [
        139,
        220,
        9,
        3,
        4,
        13,
        1,
        10,
        13,
        20
      ]
    },
    {
      "Serial No. Of Polling Station": 84,
      "Total Number of valid votes": 402,
      "Number of Rejected votes": 0,
      "NOTA": 31,
      "Total": 433,
      "candidate_votes": [
        81,
        242,
        14,
        6,
        4,
        6,
        8,
        6,
        16,
        19
      ]
    },
    {
      "Serial No. Of Polling Station": 85,
      "Total Number of valid votes": 269,
      "Number of Rejected votes": 0,
      "NOTA": 27,
      "Total": 296,
      "candidate_votes": [
        79,
        136,
        2,
        4,
        5,
        6,
        3,
        11,
        10,
        13
      ]
    },
    {
      "Serial No. Of Polling Station": 86,
      "Total Number of valid votes": 770,
      "Number of Rejected votes": 0,
      "NOTA": 32,
      "Total": 802,
      "candidate_votes": [
        235,
        435,
        26,
        0,
        4,
        8,
        6,
        9,
        17,
        30
      ]
    },
    {
      "Serial No. Of Polling Station": 87,
      "Total Number of valid votes": 603,
      "Number of Rejected votes": 0,
      "NOTA": 28,
      "Total": 631,
      "candidate_votes": [
        279,
        270,
        13,
        6,
        4,
        2,
        4,
        5,
        4,
        16
      ]
    },
    {
      "Serial No. Of Polling Station": 88,
      "Total Number of valid votes": 541,
      "Number of Rejected votes": 0,
      "NOTA": 4,
      "Total": 545,
      "candidate_votes": [
        214,
        298,
        8,
        0,
        2,
        2,
        10,
        3,
        2,
        2
      ]
    },
    {
      "Serial No. Of Polling Station": 89,
      "Total Number of valid votes": 758,
      "Number of Rejected votes": 0,
      "NOTA": 15,
      "Total": 773,
      "candidate_votes": [
        404,
        312,
        16,
        2,
        2,
        2,
        15,
        2,
        1,
        2
      ]
    },
    {
      "Serial No. Of Polling Station": 90,
      "Total Number of valid votes": 645,
      "Number of Rejected votes": 0,
      "NOTA": 23,
      "Total": 668,
      "candidate_votes": [
        307,
        301,
        9,
        3,
        1,
        5,
        1,
        4,
        6,
        8
      ]
    },
    {
      "Serial No. Of Polling Station": 91,
      "Total Number of valid votes": 574,
      "Number of Rejected votes": 0,
      "NOTA": 17,
      "Total": 591,
      "candidate_votes": [
        198,
        332,
        11,
        6,
        3,
        4,
        4,
        1,
        7,
        8
      ]
    },
    {
      "Serial No. Of Polling Station": 92,
      "Total Number of valid votes": 599,
      "Number of Rejected votes": 0,
      "NOTA": 12,
      "Total": 611,
      "candidate_votes": [
        177,
        377,
        12,
        4,
        2,
        2,
        5,
        10,
        7,
        3
      ]
    },
    {
      "Serial No. Of Polling Station": 93,
      "Total Number of valid votes": 773,
      "Number of Rejected votes": 0,
      "NOTA": 30,
      "Total": 803,
      "candidate_votes": [
        359,
        383,
        5,
        2,
        1,
        2,
        4,
        2,
        7,
        8
      ]
    },
    {
      "Serial No. Of Polling Station": 94,
      "Total Number of valid votes": 474,
      "Number of Rejected votes": 0,
      "NOTA": 8,
      "Total": 482,
      "candidate_votes": [
        156,
        292,
        7,
        1,
        1,
        1,
        0,
        3,
        5,
        8
      ]
    },
    {
      "Serial No. Of Polling Station": 95,
      "Total Number of valid votes": 798,
      "Number of Rejected votes": 0,
      "NOTA": 15,
      "Total": 813,
      "candidate_votes": [
        511,
        243,
        9,
        3,
        0,
        7,
        5,
        3,
        7,
        10
      ]
    },
    {
      "Serial No. Of Polling Station": 96,
      "Total Number of valid votes": 586,
      "Number of Rejected votes": 0,
      "NOTA": 10,
      "Total": 596,
      "candidate_votes": [
        359,
        204,
        4,
        1,
        4,
        2,
        2,
        0,
        4,
        6
      ]
    },
    {
      "Serial No. Of Polling Station": 97,
      "Total Number of valid votes": 560,
      "Number of Rejected votes": 0,
      "NOTA": 6,
      "Total": 566,
      "candidate_votes": [
        340,
        193,
        8,
        3,
        1,
        2,
        2,
        1,
        8,
        2
      ]
    },
    {
      "Serial No. Of Polling Station": 98,
      "Total Number of valid votes": 741,
      "Number of Rejected votes": 0,
      "NOTA": 8,
      "Total": 749,
      "candidate_votes": [
        72,
        561,
        81,
        1,
        1,
        3,
        6,
        2,
        7,
        7
      ]
    },
    {
      "Serial No. Of Polling Station": 99,
      "Total Number of valid votes": 844,
      "Number of Rejected votes": 0,
      "NOTA": 17,
      "Total": 861,
      "candidate_votes": [
        188,
        584,
        40,
        1,
        2,
        1,
        11,
        3,
        6,
        8
      ]
    },
    {
      "Serial No. Of Polling Station": 100,
      "Total Number of valid votes": 741,
      "Number of Rejected votes": 0,
      "NOTA": 5,
      "Total": 746,
      "candidate_votes": [
        258,
        453,
        6,
        3,
        4,
        2,
        1,
        3,
        5,
        6
      ]
    },
    {
      "Serial No. Of Polling Station": 101,
      "Total Number of valid votes": 673,
      "Number of Rejected votes": 0,
      "NOTA": 10,
      "Total": 683,
      "candidate_votes": [
        205,
        447,
        3,
        0,
        0,
        1,
        3,
        1,
        8,
        5
      ]
    },
    {
      "Serial No. Of Polling Station": 102,
      "Total Number of valid votes": 605,
      "Number of Rejected votes": 0,
      "NOTA": 9,
      "Total": 614,
      "candidate_votes": [
        297,
        291,
        4,
        0,
        1,
        1,
        2,
        1,
        5,
        3
      ]
    },
    {
      "Serial No. Of Polling Station": 103,
      "Total Number of valid votes": 618,
      "Number of Rejected votes": 0,
      "NOTA": 17,
      "Total": 635,
      "candidate_votes": [
        212,
        378,
        2,
        1,
        5,
        3,
        5,
        3,
        3,
        6
      ]
    },
    {
      "Serial No. Of Polling Station": 104,
      "Total Number of valid votes": 203,
      "Number of Rejected votes": 0,
      "NOTA": 7,
      "Total": 210,
      "candidate_votes": [
        52,
        133,
        6,
        3,
        1,
        1,
        5,
        1,
        1,
        0
      ]
    },
    {
      "Serial No. Of Polling Station": 105,
      "Total Number of valid votes": 624,
      "Number of Rejected votes": 0,
      "NOTA": 42,
      "Total": 666,
      "candidate_votes": [
        155,
        358,
        13,
        9,
        10,
        13,
        12,
        9,
        15,
        30
      ]
    },
    {
      "Serial No. Of Polling Station": 106,
      "Total Number of valid votes": 730,
      "Number of Rejected votes": 0,
      "NOTA": 53,
      "Total": 783,
      "candidate_votes": [
        180,
        446,
        21,
        8,
        9,
        7,
        9,
        7,
        16,
        27
      ]
    },
    {
      "Serial No. Of Polling Station": 107,
      "Total Number of valid votes": 624,
      "Number of Rejected votes": 0,
      "NOTA": 116,
      "Total": 740,
      "candidate_votes": [
        136,
        382,
        27,
        3,
        4,
        6,
        19,
        10,
        16,
        21
      ]
    },
    {
      "Serial No. Of Polling Station": 108,
      "Total Number of valid votes": 608,
      "Number of Rejected votes": 0,
      "NOTA": 69,
      "Total": 677,
      "candidate_votes": [
        138,
        366,
        16,
        10,
        6,
        6,
        15,
        13,
        12,
        26
      ]
    },
    {
      "Serial No. Of Polling Station": 109,
      "Total Number of valid votes": 439,
      "Number of Rejected votes": 0,
      "NOTA": 30,
      "Total": 469,
      "candidate_votes": [
        57,
        332,
        13,
        4,
        1,
        2,
        4,
        3,
        9,
        14
      ]
    },
    {
      "Serial No. Of Polling Station": 110,
      "Total Number of valid votes": 467,
      "Number of Rejected votes": 0,
      "NOTA": 48,
      "Total": 515,
      "candidate_votes": [
        48,
        360,
        9,
        1,
        2,
        2,
        5,
        6,
        18,
        16
      ]
    },
    {
      "Serial No. Of Polling Station": 111,
      "Total Number of valid votes": 352,
      "Number of Rejected votes": 0,
      "NOTA": 20,
      "Total": 372,
      "candidate_votes": [
        64,
        263,
        4,
        1,
        2,
        5,
        3,
        1,
        1,
        8
      ]
    },
    {
      "Serial No. Of Polling Station": 112,
      "Total Number of valid votes": 273,
      "Number of Rejected votes": 0,
      "NOTA": 15,
      "Total": 288,
      "candidate_votes": [
        19,
        218,
        10,
        2,
        4,
        2,
        2,
        2,
        5,
        9
      ]
    },
    {
      "Serial No. Of Polling Station": 113,
      "Total Number of valid votes": 198,
      "Number of Rejected votes": 0,
      "NOTA": 11,
      "Total": 209,
      "candidate_votes": [
        28,
        123,
        10,
        7,
        4,
        8,
        7,
        2,
        6,
        3
      ]
    },
    {
      "Serial No. Of Polling Station": 114,
      "Total Number of valid votes": 326,
      "Number of Rejected votes": 0,
      "NOTA": 59,
      "Total": 385,
      "candidate_votes": [
        21,
        248,
        6,
        6,
        0,
        1,
        4,
        10,
        10,
        20
      ]
    },
    {
      "Serial No. Of Polling Station": 115,
      "Total Number of valid votes": 528,
      "Number of Rejected votes": 0,
      "NOTA": 28,
      "Total": 556,
      "candidate_votes": [
        110,
        367,
        7,
        3,
        5,
        5,
        1,
        5,
        11,
        14
      ]
    },
    {
      "Serial No. Of Polling Station": 116,
      "Total Number of valid votes": 199,
      "Number of Rejected votes": 0,
      "NOTA": 15,
      "Total": 214,
      "candidate_votes": [
        22,
        158,
        5,
        3,
        0,
        1,
        1,
        1,
        2,
        6
      ]
    },
    {
      "Serial No. Of Polling Station": 117,
      "Total Number of valid votes": 453,
      "Number of Rejected votes": 0,
      "NOTA": 11,
      "Total": 464,
      "candidate_votes": [
        26,
        393,
        6,
        2,
        2,
        3,
        2,
        3,
        6,
        10
      ]
    },
    {
      "Serial No. Of Polling Station": 118,
      "Total Number of valid votes": 462,
      "Number of Rejected votes": 0,
      "NOTA": 105,
      "Total": 567,
      "candidate_votes": [
        96,
        275,
        9,
        6,
        6,
        4,
        8,
        9,
        13,
        36
      ]
    },
    {
      "Serial No. Of Polling Station": 119,
      "Total Number of valid votes": 544,
      "Number of Rejected votes": 0,
      "NOTA": 44,
      "Total": 588,
      "candidate_votes": [
        118,
        374,
        9,
        5,
        2,
        6,
        3,
        3,
        8,
        16
      ]
    },
    {
      "Serial No. Of Polling Station": 120,
      "Total Number of valid votes": 366,
      "Number of Rejected votes": 0,
      "NOTA": 15,
      "Total": 381,
      "candidate_votes": [
        38,
        263,
        19,
        6,
        2,
        1,
        3,
        13,
        6,
        15
      ]
    },
    {
      "Serial No. Of Polling Station": 121,
      "Total Number of valid votes": 516,
      "Number of Rejected votes": 0,
      "NOTA": 20,
      "Total": 536,
      "candidate_votes": [
        67,
        410,
        13,
        4,
        2,
        5,
        3,
        3,
        4,
        5
      ]
    },
    {
      "Serial No. Of Polling Station": 122,
      "Total Number of valid votes": 400,
      "Number of Rejected votes": 0,
      "NOTA": 19,
      "Total": 419,
      "candidate_votes": [
        127,
        234,
        8,
        1,
        1,
        4,
        1,
        5,
        8,
        11
      ]
    },
    {
      "Serial No. Of Polling Station": 123,
      "Total Number of valid votes": 504,
      "Number of Rejected votes": 0,
      "NOTA": 12,
      "Total": 516,
      "candidate_votes": [
        59,
        424,
        3,
        1,
        0,
        3,
        1,
        3,
        3,
        7
      ]
    },
    {
      "Serial No. Of Polling Station": 124,
      "Total Number of valid votes": 411,
      "Number of Rejected votes": 0,
      "NOTA": 15,
      "Total": 426,
      "candidate_votes": [
        157,
        231,
        5,
        1,
        2,
        3,
        2,
        4,
        3,
        3
      ]
    },
    {
      "Serial No. Of Polling Station": 125,
      "Total Number of valid votes": 402,
      "Number of Rejected votes": 0,
      "NOTA": 16,
      "Total": 418,
      "candidate_votes": [
        188,
        193,
        4,
        1,
        0,
        0,
        1,
        2,
        5,
        8
      ]
    },
    {
      "Serial No. Of Polling Station": 126,
      "Total Number of valid votes": 489,
      "Number of Rejected votes": 0,
      "NOTA": 4,
      "Total": 493,
      "candidate_votes": [
        141,
        336,
        4,
        0,
        3,
        1,
        1,
        1,
        1,
        1
      ]
    },
    {
      "Serial No. Of Polling Station": 127,
      "Total Number of valid votes": 737,
      "Number of Rejected votes": 0,
      "NOTA": 13,
      "Total": 750,
      "candidate_votes": [
        269,
        445,
        17,
        0,
        0,
        1,
        2,
        1,
        0,
        2
      ]
    },
    {
      "Serial No. Of Polling Station": 128,
      "Total Number of valid votes": 458,
      "Number of Rejected votes": 0,
      "NOTA": 9,
      "Total": 467,
      "candidate_votes": [
        200,
        242,
        10,
        0,
        0,
        1,
        0,
        5,
        0,
        0
      ]
    },
    {
      "Serial No. Of Polling Station": 129,
      "Total Number of valid votes": 437,
      "Number of Rejected votes": 0,
      "NOTA": 5,
      "Total": 442,
      "candidate_votes": [
        168,
        247,
        9,
        0,
        0,
        2,
        5,
        2,
        0,
        4
      ]
    },
    {
      "Serial No. Of Polling Station": 130,
      "Total Number of valid votes": 506,
      "Number of Rejected votes": 0,
      "NOTA": 7,
      "Total": 513,
      "candidate_votes": [
        201,
        268,
        26,
        0,
        0,
        2,
        4,
        0,
        1,
        4
      ]
    },
    {
      "Serial No. Of Polling Station": 131,
      "Total Number of valid votes": 563,
      "Number of Rejected votes": 0,
      "NOTA": 8,
      "Total": 571,
      "candidate_votes": [
        238,
        304,
        9,
        0,
        3,
        1,
        2,
        0,
        3,
        3
      ]
    },
    {
      "Serial No. Of Polling Station": 132,
      "Total Number of valid votes": 667,
      "Number of Rejected votes": 0,
      "NOTA": 15,
      "Total": 682,
      "candidate_votes": [
        299,
        351,
        7,
        0,
        1,
        1,
        4,
        2,
        2,
        0
      ]
    },
    {
      "Serial No. Of Polling Station": 133,
      "Total Number of valid votes": 586,
      "Number of Rejected votes": 0,
      "NOTA": 9,
      "Total": 595,
      "candidate_votes": [
        185,
        388,
        7,
        0,
        1,
        1,
        0,
        3,
        1,
        0
      ]
    },
    {
      "Serial No. Of Polling Station": 134,
      "Total Number of valid votes": 482,
      "Number of Rejected votes": 0,
      "NOTA": 7,
      "Total": 489,
      "candidate_votes": [
        239,
        229,
        2,
        2,
        2,
        2,
        1,
        3,
        1,
        1
      ]
    },
    {
      "Serial No. Of Polling Station": 135,
      "Total Number of valid votes": 561,
      "Number of Rejected votes": 0,
      "NOTA": 9,
      "Total": 570,
      "candidate_votes": [
        382,
        143,
        7,
        4,
        4,
        4,
        3,
        6,
        4,
        4
      ]
    },
    {
      "Serial No. Of Polling Station": 136,
      "Total Number of valid votes": 503,
      "Number of Rejected votes": 0,
      "NOTA": 7,
      "Total": 510,
      "candidate_votes": [
        293,
        194,
        3,
        2,
        1,
        0,
        6,
        1,
        3,
        0
      ]
    },
    {
      "Serial No. Of Polling Station": 137,
      "Total Number of valid votes": 732,
      "Number of Rejected votes": 0,
      "NOTA": 11,
      "Total": 743,
      "candidate_votes": [
        240,
        462,
        17,
        1,
        0,
        1,
        3,
        4,
        2,
        2
      ]
    },
    {
      "Serial No. Of Polling Station": 138,
      "Total Number of valid votes": 696,
      "Number of Rejected votes": 0,
      "NOTA": 9,
      "Total": 705,
      "candidate_votes": [
        331,
        331,
        22,
        0,
        2,
        1,
        3,
        1,
        3,
        2
      ]
    },
    {
      "Serial No. Of Polling Station": 139,
      "Total Number of valid votes": 699,
      "Number of Rejected votes": 0,
      "NOTA": 10,
      "Total": 709,
      "candidate_votes": [
        255,
        419,
        12,
        2,
        1,
        3,
        0,
        2,
        2,
        3
      ]
    },
    {
      "Serial No. Of Polling Station": 140,
      "Total Number of valid votes": 634,
      "Number of Rejected votes": 0,
      "NOTA": 8,
      "Total": 642,
      "candidate_votes": [
        319,
        290,
        9,
        3,
        4,
        1,
        0,
        3,
        1,
        4
      ]
    },
    {
      "Serial No. Of Polling Station": 141,
      "Total Number of valid votes": 603,
      "Number of Rejected votes": 0,
      "NOTA": 13,
      "Total": 616,
      "candidate_votes": [
        336,
        250,
        7,
        2,
        1,
        2,
        1,
        2,
        1,
        1
      ]
    },
    {
      "Serial No. Of Polling Station": 142,
      "Total Number of valid votes": 342,
      "Number of Rejected votes": 0,
      "NOTA": 11,
      "Total": 353,
      "candidate_votes": [
        153,
        174,
        10,
        1,
        1,
        1,
        1,
        0,
        1,
        0
      ]
    },
    {
      "Serial No. Of Polling Station": 143,
      "Total Number of valid votes": 437,
      "Number of Rejected votes": 0,
      "NOTA": 10,
      "Total": 447,
      "candidate_votes": [
        237,
        178,
        7,
        2,
        3,
        2,
        2,
        0,
        3,
        3
      ]
    },
    {
      "Serial No. Of Polling Station": 144,
      "Total Number of valid votes": 581,
      "Number of Rejected votes": 0,
      "NOTA": 8,
      "Total": 589,
      "candidate_votes": [
        305,
        266,
        8,
        0,
        0,
        0,
        1,
        0,
        0,
        1
      ]
    },
    {
      "Serial No. Of Polling Station": 145,
      "Total Number of valid votes": 713,
      "Number of Rejected votes": 0,
      "NOTA": 6,
      "Total": 719,
      "candidate_votes": [
        106,
        585,
        10,
        0,
        2,
        2,
        4,
        0,
        0,
        4
      ]
    },
    {
      "Serial No. Of Polling Station": 146,
      "Total Number of valid votes": 547,
      "Number of Rejected votes": 0,
      "NOTA": 10,
      "Total": 557,
      "candidate_votes": [
        180,
        342,
        8,
        2,
        1,
        1,
        2,
        3,
        4,
        4
      ]
    },
    {
      "Serial No. Of Polling Station": 147,
      "Total Number of valid votes": 583,
      "Number of Rejected votes": 0,
      "NOTA": 10,
      "Total": 593,
      "candidate_votes": [
        441,
        130,
        2,
        1,
        2,
        3,
        1,
        1,
        1,
        1
      ]
    },
    {
      "Serial No. Of Polling Station": 148,
      "Total Number of valid votes": 507,
      "Number of Rejected votes": 0,
      "NOTA": 6,
      "Total": 513,
      "candidate_votes": [
        219,
        276,
        4,
        2,
        1,
        2,
        1,
        1,
        1,
        0
      ]
    },
    {
      "Serial No. Of Polling Station": 149,
      "Total Number of valid votes": 565,
      "Number of Rejected votes": 0,
      "NOTA": 10,
      "Total": 575,
      "candidate_votes": [
        377,
        183,
        1,
        1,
        2,
        0,
        0,
        0,
        0,
        1
      ]
    },
    {
      "Serial No. Of Polling Station": 150,
      "Total Number of valid votes": 298,
      "Number of Rejected votes": 0,
      "NOTA": 6,
      "Total": 304,
      "candidate_votes": [
        191,
        101,
        2,
        0,
        0,
        0,
        3,
        0,
        1,
        0
      ]
    },
    {
      "Serial No. Of Polling Station": 151,
      "Total Number of valid votes": 598,
      "Number of Rejected votes": 0,
      "NOTA": 12,
      "Total": 610,
      "candidate_votes": [
        154,
        418,
        8,
        1,
        1,
        2,
        3,
        2,
        5,
        4
      ]
    },
    {
      "Serial No. Of Polling Station": 152,
      "Total Number of valid votes": 686,
      "Number of Rejected votes": 0,
      "NOTA": 16,
      "Total": 702,
      "candidate_votes": [
        506,
        159,
        4,
        1,
        2,
        0,
        2,
        0,
        8,
        4
      ]
    },
    {
      "Serial No. Of Polling Station": 153,
      "Total Number of valid votes": 562,
      "Number of Rejected votes": 0,
      "NOTA": 8,
      "Total": 570,
      "candidate_votes": [
        277,
        258,
        6,
        1,
        3,
        4,
        2,
        5,
        3,
        3
      ]
    },
    {
      "Serial No. Of Polling Station": 154,
      "Total Number of valid votes": 923,
      "Number of Rejected votes": 0,
      "NOTA": 23,
      "Total": 946,
      "candidate_votes": [
        546,
        313,
        37,
        1,
        0,
        2,
        5,
        5,
        8,
        6
      ]
    },
    {
      "Serial No. Of Polling Station": 155,
      "Total Number of valid votes": 883,
      "Number of Rejected votes": 0,
      "NOTA": 18,
      "Total": 901,
      "candidate_votes": [
        396,
        432,
        20,
        2,
        3,
        5,
        12,
        4,
        5,
        4
      ]
    },
    {
      "Serial No. Of Polling Station": 156,
      "Total Number of valid votes": 676,
      "Number of Rejected votes": 0,
      "NOTA": 10,
      "Total": 686,
      "candidate_votes": [
        233,
        417,
        4,
        2,
        2,
        3,
        1,
        2,
        5,
        7
      ]
    },
    {
      "Serial No. Of Polling Station": 157,
      "Total Number of valid votes": 772,
      "Number of Rejected votes": 0,
      "NOTA": 8,
      "Total": 780,
      "candidate_votes": [
        120,
        578,
        37,
        3,
        0,
        8,
        6,
        10,
        4,
        6
      ]
    },
    {
      "Serial No. Of Polling Station": 158,
      "Total Number of valid votes": 572,
      "Number of Rejected votes": 0,
      "NOTA": 7,
      "Total": 579,
      "candidate_votes": [
        370,
        179,
        6,
        0,
        0,
        3,
        2,
        3,
        7,
        2
      ]
    },
    {
      "Serial No. Of Polling Station": 159,
      "Total Number of valid votes": 392,
      "Number of Rejected votes": 0,
      "NOTA": 9,
      "Total": 401,
      "candidate_votes": [
        229,
        150,
        3,
        0,
        0,
        1,
        0,
        3,
        1,
        5
      ]
    },
    {
      "Serial No. Of Polling Station": 160,
      "Total Number of valid votes": 583,
      "Number of Rejected votes": 0,
      "NOTA": 18,
      "Total": 601,
      "candidate_votes": [
        132,
        391,
        24,
        4,
        2,
        4,
        5,
        2,
        11,
        8
      ]
    },
    {
      "Serial No. Of Polling Station": 161,
      "Total Number of valid votes": 643,
      "Number of Rejected votes": 0,
      "NOTA": 15,
      "Total": 658,
      "candidate_votes": [
        89,
        497,
        20,
        4,
        2,
        10,
        4,
        4,
        6,
        7
      ]
    },
    {
      "Serial No. Of Polling Station": 162,
      "Total Number of valid votes": 686,
      "Number of Rejected votes": 0,
      "NOTA": 8,
      "Total": 694,
      "candidate_votes": [
        335,
        328,
        7,
        2,
        1,
        0,
        2,
        3,
        5,
        3
      ]
    },
    {
      "Serial No. Of Polling Station": 163,
      "Total Number of valid votes": 522,
      "Number of Rejected votes": 0,
      "NOTA": 15,
      "Total": 537,
      "candidate_votes": [
        219,
        278,
        4,
        1,
        1,
        5,
        3,
        3,
        1,
        7
      ]
    },
    {
      "Serial No. Of Polling Station": 164,
      "Total Number of valid votes": 556,
      "Number of Rejected votes": 0,
      "NOTA": 16,
      "Total": 572,
      "candidate_votes": [
        197,
        339,
        7,
        3,
        0,
        3,
        1,
        2,
        2,
        2
      ]
    },
    {
      "Serial No. Of Polling Station": 165,
      "Total Number of valid votes": 785,
      "Number of Rejected votes": 0,
      "NOTA": 33,
      "Total": 818,
      "candidate_votes": [
        231,
        453,
        31,
        7,
        3,
        8,
        8,
        9,
        18,
        17
      ]
    },
    {
      "Serial No. Of Polling Station": 166,
      "Total Number of valid votes": 282,
      "Number of Rejected votes": 0,
      "NOTA": 19,
      "Total": 301,
      "candidate_votes": [
        96,
        141,
        10,
        2,
        1,
        5,
        3,
        5,
        8,
        11
      ]
    },
    {
      "Serial No. Of Polling Station": 167,
      "Total Number of valid votes": 526,
      "Number of Rejected votes": 0,
      "NOTA": 37,
      "Total": 563,
      "candidate_votes": [
        239,
        218,
        23,
        2,
        4,
        8,
        4,
        4,
        12,
        12
      ]
    },
    {
      "Serial No. Of Polling Station": 168,
      "Total Number of valid votes": 766,
      "Number of Rejected votes": 0,
      "NOTA": 26,
      "Total": 792,
      "candidate_votes": [
        334,
        388,
        14,
        3,
        1,
        2,
        4,
        8,
        3,
        9
      ]
    },
    {
      "Serial No. Of Polling Station": 169,
      "Total Number of valid votes": 381,
      "Number of Rejected votes": 0,
      "NOTA": 11,
      "Total": 392,
      "candidate_votes": [
        98,
        254,
        7,
        6,
        1,
        1,
        4,
        0,
        4,
        6
      ]
    },
    {
      "Serial No. Of Polling Station": 170,
      "Total Number of valid votes": 434,
      "Number of Rejected votes": 0,
      "NOTA": 14,
      "Total": 448,
      "candidate_votes": [
        117,
        287,
        7,
        0,
        2,
        2,
        1,
        3,
        6,
        9
      ]
    },
    {
      "Serial No. Of Polling Station": 171,
      "Total Number of valid votes": 403,
      "Number of Rejected votes": 0,
      "NOTA": 61,
      "Total": 464,
      "candidate_votes": [
        68,
        265,
        18,
        7,
        3,
        5,
        7,
        4,
        12,
        14
      ]
    },
    {
      "Serial No. Of Polling Station": 172,
      "Total Number of valid votes": 735,
      "Number of Rejected votes": 0,
      "NOTA": 53,
      "Total": 788,
      "candidate_votes": [
        239,
        442,
        17,
        2,
        5,
        4,
        6,
        3,
        5,
        12
      ]
    },
    {
      "Serial No. Of Polling Station": 173,
      "Total Number of valid votes": 488,
      "Number of Rejected votes": 0,
      "NOTA": 46,
      "Total": 534,
      "candidate_votes": [
        159,
        276,
        9,
        2,
        3,
        3,
        4,
        5,
        11,
        16
      ]
    },
    {
      "Serial No. Of Polling Station": 174,
      "Total Number of valid votes": 708,
      "Number of Rejected votes": 0,
      "NOTA": 39,
      "Total": 747,
      "candidate_votes": [
        232,
        398,
        18,
        6,
        5,
        5,
        7,
        10,
        10,
        17
      ]
    },
    {
      "Serial No. Of Polling Station": 175,
      "Total Number of valid votes": 176,
      "Number of Rejected votes": 0,
      "NOTA": 16,
      "Total": 192,
      "candidate_votes": [
        50,
        113,
        3,
        1,
        2,
        0,
        0,
        2,
        4,
        1
      ]
    },
    {
      "Serial No. Of Polling Station": 176,
      "Total Number of valid votes": 244,
      "Number of Rejected votes": 0,
      "NOTA": 16,
      "Total": 260,
      "candidate_votes": [
        24,
        199,
        6,
        2,
        1,
        1,
        0,
        2,
        6,
        3
      ]
    },
    {
      "Serial No. Of Polling Station": 177,
      "Total Number of valid votes": 500,
      "Number of Rejected votes": 0,
      "NOTA": 12,
      "Total": 512,
      "candidate_votes": [
        23,
        445,
        13,
        2,
        2,
        1,
        3,
        1,
        4,
        6
      ]
    },
    {
      "Serial No. Of Polling Station": 178,
      "Total Number of valid votes": 53,
      "Number of Rejected votes": 0,
      "NOTA": 1,
      "Total": 54,
      "candidate_votes": [
        10,
        41,
        2,
        0,
        0,
        0,
        0,
        0,
        0,
        0
      ]
    },
    {
      "Serial No. Of Polling Station": 179,
      "Total Number of valid votes": 558,
      "Number of Rejected votes": 0,
      "NOTA": 23,
      "Total": 581,
      "candidate_votes": [
        170,
        351,
        10,
        2,
        1,
        2,
        3,
        3,
        3,
        13
      ]
    },
    {
      "Serial No. Of Polling Station": 180,
      "Total Number of valid votes": 545,
      "Number of Rejected votes": 0,
      "NOTA": 45,
      "Total": 590,
      "candidate_votes": [
        204,
        281,
        10,
        4,
        2,
        6,
        5,
        7,
        8,
        18
      ]
    },
    {
      "Serial No. Of Polling Station": 181,
      "Total Number of valid votes": 581,
      "Number of Rejected votes": 0,
      "NOTA": 45,
      "Total": 626,
      "candidate_votes": [
        165,
        362,
        5,
        2,
        5,
        5,
        5,
        7,
        8,
        17
      ]
    },
    {
      "Serial No. Of Polling Station": 182,
      "Total Number of valid votes": 306,
      "Number of Rejected votes": 0,
      "NOTA": 14,
      "Total": 320,
      "candidate_votes": [
        56,
        219,
        15,
        2,
        0,
        2,
        1,
        3,
        3,
        5
      ]
    },
    {
      "Serial No. Of Polling Station": 183,
      "Total Number of valid votes": 322,
      "Number of Rejected votes": 0,
      "NOTA": 16,
      "Total": 338,
      "candidate_votes": [
        33,
        270,
        6,
        1,
        1,
        1,
        2,
        0,
        1,
        7
      ]
    },
    {
      "Serial No. Of Polling Station": 184,
      "Total Number of valid votes": 344,
      "Number of Rejected votes": 0,
      "NOTA": 8,
      "Total": 352,
      "candidate_votes": [
        90,
        223,
        10,
        4,
        3,
        3,
        1,
        0,
        5,
        5
      ]
    },
    {
      "Serial No. Of Polling Station": 185,
      "Total Number of valid votes": 353,
      "Number of Rejected votes": 0,
      "NOTA": 35,
      "Total": 388,
      "candidate_votes": [
        105,
        195,
        7,
        4,
        3,
        6,
        8,
        6,
        7,
        12
      ]
    },
    {
      "Serial No. Of Polling Station": 186,
      "Total Number of valid votes": 621,
      "Number of Rejected votes": 0,
      "NOTA": 12,
      "Total": 633,
      "candidate_votes": [
        300,
        304,
        5,
        0,
        1,
        4,
        2,
        1,
        0,
        4
      ]
    },
    {
      "Serial No. Of Polling Station": 187,
      "Total Number of valid votes": 503,
      "Number of Rejected votes": 0,
      "NOTA": 11,
      "Total": 514,
      "candidate_votes": [
        163,
        321,
        4,
        2,
        2,
        2,
        4,
        0,
        0,
        5
      ]
    },
    {
      "Serial No. Of Polling Station": 188,
      "Total Number of valid votes": 621,
      "Number of Rejected votes": 0,
      "NOTA": 22,
      "Total": 643,
      "candidate_votes": [
        129,
        451,
        16,
        1,
        0,
        3,
        4,
        4,
        6,
        7
      ]
    },
    {
      "Serial No. Of Polling Station": 189,
      "Total Number of valid votes": 296,
      "Number of Rejected votes": 0,
      "NOTA": 19,
      "Total": 315,
      "candidate_votes": [
        165,
        111,
        2,
        1,
        1,
        2,
        1,
        6,
        1,
        6
      ]
    },
    {
      "Serial No. Of Polling Station": 190,
      "Total Number of valid votes": 588,
      "Number of Rejected votes": 0,
      "NOTA": 39,
      "Total": 627,
      "candidate_votes": [
        288,
        241,
        20,
        1,
        1,
        6,
        4,
        4,
        11,
        12
      ]
    },
    {
      "Serial No. Of Polling Station": 191,
      "Total Number of valid votes": 219,
      "Number of Rejected votes": 0,
      "NOTA": 17,
      "Total": 236,
      "candidate_votes": [
        68,
        132,
        3,
        1,
        0,
        3,
        2,
        0,
        3,
        7
      ]
    },
    {
      "Serial No. Of Polling Station": 192,
      "Total Number of valid votes": 267,
      "Number of Rejected votes": 0,
      "NOTA": 9,
      "Total": 276,
      "candidate_votes": [
        220,
        37,
        5,
        2,
        0,
        1,
        0,
        1,
        0,
        1
      ]
    },
    {
      "Serial No. Of Polling Station": 193,
      "Total Number of valid votes": 465,
      "Number of Rejected votes": 0,
      "NOTA": 33,
      "Total": 498,
      "candidate_votes": [
        122,
        273,
        26,
        3,
        1,
        7,
        7,
        4,
        8,
        14
      ]
    },
    {
      "Serial No. Of Polling Station": 194,
      "Total Number of valid votes": 500,
      "Number of Rejected votes": 0,
      "NOTA": 20,
      "Total": 520,
      "candidate_votes": [
        88,
        369,
        16,
        1,
        1,
        2,
        4,
        2,
        11,
        6
      ]
    },
    {
      "Serial No. Of Polling Station": 195,
      "Total Number of valid votes": 667,
      "Number of Rejected votes": 0,
      "NOTA": 25,
      "Total": 692,
      "candidate_votes": [
        377,
        210,
        48,
        2,
        2,
        2,
        2,
        5,
        10,
        9
      ]
    },
    {
      "Serial No. Of Polling Station": 196,
      "Total Number of valid votes": 574,
      "Number of Rejected votes": 0,
      "NOTA": 36,
      "Total": 610,
      "candidate_votes": [
        218,
        265,
        52,
        3,
        1,
        2,
        13,
        2,
        11,
        7
      ]
    },
    {
      "Serial No. Of Polling Station": 197,
      "Total Number of valid votes": 345,
      "Number of Rejected votes": 0,
      "NOTA": 19,
      "Total": 364,
      "candidate_votes": [
        225,
        88,
        6,
        1,
        1,
        4,
        4,
        6,
        8,
        2
      ]
    },
    {
      "Serial No. Of Polling Station": 198,
      "Total Number of valid votes": 220,
      "Number of Rejected votes": 0,
      "NOTA": 13,
      "Total": 233,
      "candidate_votes": [
        63,
        127,
        5,
        1,
        3,
        1,
        0,
        6,
        0,
        14
      ]
    },
    {
      "Serial No. Of Polling Station": 199,
      "Total Number of valid votes": 597,
      "Number of Rejected votes": 0,
      "NOTA": 29,
      "Total": 626,
      "candidate_votes": [
        282,
        237,
        12,
        1,
        7,
        14,
        7,
        14,
        14,
        9
      ]
    },
    {
      "Serial No. Of Polling Station": 200,
      "Total Number of valid votes": 740,
      "Number of Rejected votes": 0,
      "NOTA": 12,
      "Total": 752,
      "candidate_votes": [
        43,
        624,
        41,
        2,
        2,
        7,
        5,
        6,
        5,
        5
      ]
    },
    {
      "Serial No. Of Polling Station": 201,
      "Total Number of valid votes": 454,
      "Number of Rejected votes": 0,
      "NOTA": 8,
      "Total": 462,
      "candidate_votes": [
        155,
        265,
        7,
        1,
        4,
        3,
        3,
        2,
        9,
        5
      ]
    },
    {
      "Serial No. Of Polling Station": 202,
      "Total Number of valid votes": 365,
      "Number of Rejected votes": 0,
      "NOTA": 5,
      "Total": 370,
      "candidate_votes": [
        247,
        99,
        8,
        1,
        2,
        0,
        1,
        2,
        3,
        2
      ]
    },
    {
      "Serial No. Of Polling Station": 203,
      "Total Number of valid votes": 638,
      "Number of Rejected votes": 0,
      "NOTA": 25,
      "Total": 663,
      "candidate_votes": [
        191,
        334,
        68,
        2,
        6,
        11,
        6,
        2,
        11,
        7
      ]
    },
    {
      "Serial No. Of Polling Station": 204,
      "Total Number of valid votes": 330,
      "Number of Rejected votes": 0,
      "NOTA": 5,
      "Total": 335,
      "candidate_votes": [
        186,
        126,
        4,
        0,
        0,
        1,
        0,
        1,
        4,
        8
      ]
    },
    {
      "Serial No. Of Polling Station": 205,
      "Total Number of valid votes": 496,
      "Number of Rejected votes": 0,
      "NOTA": 14,
      "Total": 510,
      "candidate_votes": [
        323,
        139,
        7,
        2,
        1,
        4,
        4,
        5,
        5,
        6
      ]
    },
    {
      "Serial No. Of Polling Station": 206,
      "Total Number of valid votes": 523,
      "Number of Rejected votes": 0,
      "NOTA": 9,
      "Total": 532,
      "candidate_votes": [
        233,
        267,
        5,
        1,
        2,
        2,
        0,
        5,
        2,
        6
      ]
    },
    {
      "Serial No. Of Polling Station": 207,
      "Total Number of valid votes": 515,
      "Number of Rejected votes": 0,
      "NOTA": 25,
      "Total": 540,
      "candidate_votes": [
        100,
        377,
        11,
        2,
        1,
        1,
        2,
        3,
        6,
        12
      ]
    },
    {
      "Serial No. Of Polling Station": 208,
      "Total Number of valid votes": 565,
      "Number of Rejected votes": 0,
      "NOTA": 16,
      "Total": 581,
      "candidate_votes": [
        91,
        441,
        16,
        3,
        1,
        3,
        1,
        0,
        4,
        5
      ]
    },
    {
      "Serial No. Of Polling Station": 209,
      "Total Number of valid votes": 206,
      "Number of Rejected votes": 0,
      "NOTA": 11,
      "Total": 217,
      "candidate_votes": [
        47,
        120,
        9,
        1,
        4,
        3,
        1,
        5,
        5,
        11
      ]
    },
    {
      "Serial No. Of Polling Station": 210,
      "Total Number of valid votes": 539,
      "Number of Rejected votes": 0,
      "NOTA": 43,
      "Total": 582,
      "candidate_votes": [
        286,
        158,
        59,
        2,
        3,
        3,
        4,
        2,
        10,
        12
      ]
    },
    {
      "Serial No. Of Polling Station": 211,
      "Total Number of valid votes": 553,
      "Number of Rejected votes": 0,
      "NOTA": 24,
      "Total": 577,
      "candidate_votes": [
        235,
        277,
        16,
        1,
        1,
        4,
        3,
        4,
        6,
        6
      ]
    },
    {
      "Serial No. Of Polling Station": 212,
      "Total Number of valid votes": 478,
      "Number of Rejected votes": 0,
      "NOTA": 38,
      "Total": 516,
      "candidate_votes": [
        133,
        267,
        19,
        3,
        3,
        9,
        3,
        8,
        18,
        15
      ]
    },
    {
      "Serial No. Of Polling Station": 213,
      "Total Number of valid votes": 345,
      "Number of Rejected votes": 0,
      "NOTA": 14,
      "Total": 359,
      "candidate_votes": [
        130,
        179,
        10,
        3,
        1,
        3,
        1,
        4,
        11,
        3
      ]
    },
    {
      "Serial No. Of Polling Station": 214,
      "Total Number of valid votes": 748,
      "Number of Rejected votes": 0,
      "NOTA": 12,
      "Total": 760,
      "candidate_votes": [
        152,
        540,
        28,
        1,
        4,
        4,
        5,
        3,
        4,
        7
      ]
    },
    {
      "Serial No. Of Polling Station": 215,
      "Total Number of valid votes": 506,
      "Number of Rejected votes": 0,
      "NOTA": 18,
      "Total": 524,
      "candidate_votes": [
        161,
        316,
        6,
        2,
        1,
        3,
        2,
        3,
        8,
        4
      ]
    },
    {
      "Serial No. Of Polling Station": 216,
      "Total Number of valid votes": 706,
      "Number of Rejected votes": 0,
      "NOTA": 21,
      "Total": 727,
      "candidate_votes": [
        181,
        385,
        89,
        5,
        10,
        3,
        5,
        7,
        12,
        9
      ]
    },
    {
      "Serial No. Of Polling Station": 217,
      "Total Number of valid votes": 576,
      "Number of Rejected votes": 0,
      "NOTA": 17,
      "Total": 593,
      "candidate_votes": [
        32,
        214,
        273,
        3,
        3,
        8,
        11,
        8,
        16,
        8
      ]
    },
    {
      "Serial No. Of Polling Station": 218,
      "Total Number of valid votes": 504,
      "Number of Rejected votes": 0,
      "NOTA": 11,
      "Total": 515,
      "candidate_votes": [
        61,
        360,
        54,
        4,
        2,
        5,
        1,
        4,
        6,
        7
      ]
    },
    {
      "Serial No. Of Polling Station": 219,
      "Total Number of valid votes": 685,
      "Number of Rejected votes": 0,
      "NOTA": 8,
      "Total": 693,
      "candidate_votes": [
        154,
        464,
        24,
        1,
        4,
        7,
        2,
        8,
        10,
        11
      ]
    },
    {
      "Serial No. Of Polling Station": 220,
      "Total Number of valid votes": 260,
      "Number of Rejected votes": 0,
      "NOTA": 6,
      "Total": 266,
      "candidate_votes": [
        82,
        157,
        7,
        3,
        0,
        1,
        1,
        2,
        2,
        5
      ]
    },
    {
      "Serial No. Of Polling Station": 221,
      "Total Number of valid votes": 585,
      "Number of Rejected votes": 0,
      "NOTA": 23,
      "Total": 608,
      "candidate_votes": [
        190,
        254,
        106,
        1,
        1,
        6,
        4,
        4,
        9,
        10
      ]
    },
    {
      "Serial No. Of Polling Station": 222,
      "Total Number of valid votes": 602,
      "Number of Rejected votes": 0,
      "NOTA": 13,
      "Total": 615,
      "candidate_votes": [
        268,
        239,
        53,
        5,
        6,
        6,
        5,
        5,
        8,
        7
      ]
    },
    {
      "Serial No. Of Polling Station": 223,
      "Total Number of valid votes": 570,
      "Number of Rejected votes": 0,
      "NOTA": 16,
      "Total": 586,
      "candidate_votes": [
        341,
        115,
        65,
        1,
        5,
        12,
        8,
        6,
        13,
        4
      ]
    },
    {
      "Serial No. Of Polling Station": 224,
      "Total Number of valid votes": 561,
      "Number of Rejected votes": 0,
      "NOTA": 14,
      "Total": 575,
      "candidate_votes": [
        334,
        154,
        38,
        5,
        2,
        8,
        3,
        4,
        8,
        5
      ]
    },
    {
      "Serial No. Of Polling Station": 225,
      "Total Number of valid votes": 379,
      "Number of Rejected votes": 0,
      "NOTA": 8,
      "Total": 387,
      "candidate_votes": [
        214,
        112,
        13,
        2,
        2,
        10,
        2,
        6,
        13,
        5
      ]
    },
    {
      "Serial No. Of Polling Station": 226,
      "Total Number of valid votes": 825,
      "Number of Rejected votes": 0,
      "NOTA": 16,
      "Total": 841,
      "candidate_votes": [
        507,
        251,
        10,
        4,
        2,
        12,
        6,
        6,
        18,
        9
      ]
    },
    {
      "Serial No. Of Polling Station": 227,
      "Total Number of valid votes": 671,
      "Number of Rejected votes": 0,
      "NOTA": 18,
      "Total": 689,
      "candidate_votes": [
        153,
        453,
        19,
        1,
        5,
        9,
        5,
        5,
        10,
        11
      ]
    },
    {
      "Serial No. Of Polling Station": 228,
      "Total Number of valid votes": 314,
      "Number of Rejected votes": 0,
      "NOTA": 20,
      "Total": 334,
      "candidate_votes": [
        130,
        161,
        7,
        2,
        1,
        3,
        1,
        0,
        7,
        2
      ]
    },
    {
      "Serial No. Of Polling Station": 229,
      "Total Number of valid votes": 605,
      "Number of Rejected votes": 0,
      "NOTA": 20,
      "Total": 625,
      "candidate_votes": [
        110,
        426,
        47,
        1,
        2,
        3,
        3,
        0,
        6,
        7
      ]
    },
    {
      "Serial No. Of Polling Station": 230,
      "Total Number of valid votes": 575,
      "Number of Rejected votes": 0,
      "NOTA": 12,
      "Total": 587,
      "candidate_votes": [
        241,
        294,
        15,
        6,
        3,
        3,
        6,
        0,
        2,
        5
      ]
    },
    {
      "Serial No. Of Polling Station": 231,
      "Total Number of valid votes": 522,
      "Number of Rejected votes": 0,
      "NOTA": 12,
      "Total": 534,
      "candidate_votes": [
        366,
        129,
        7,
        2,
        1,
        0,
        2,
        1,
        6,
        8
      ]
    },
    {
      "Serial No. Of Polling Station": 232,
      "Total Number of valid votes": 722,
      "Number of Rejected votes": 0,
      "NOTA": 20,
      "Total": 742,
      "candidate_votes": [
        321,
        340,
        32,
        4,
        2,
        5,
        3,
        2,
        7,
        6
      ]
    },
    {
      "Serial No. Of Polling Station": 233,
      "Total Number of valid votes": 272,
      "Number of Rejected votes": 0,
      "NOTA": 9,
      "Total": 281,
      "candidate_votes": [
        75,
        181,
        4,
        1,
        1,
        4,
        1,
        1,
        2,
        2
      ]
    },
    {
      "Serial No. Of Polling Station": 234,
      "Total Number of valid votes": 189,
      "Number of Rejected votes": 0,
      "NOTA": 13,
      "Total": 202,
      "candidate_votes": [
        35,
        126,
        8,
        0,
        1,
        5,
        1,
        6,
        5,
        2
      ]
    },
    {
      "Serial No. Of Polling Station": 235,
      "Total Number of valid votes": 567,
      "Number of Rejected votes": 0,
      "NOTA": 22,
      "Total": 589,
      "candidate_votes": [
        94,
        369,
        76,
        1,
        2,
        4,
        4,
        7,
        3,
        7
      ]
    },
    {
      "Serial No. Of Polling Station": 236,
      "Total Number of valid votes": 633,
      "Number of Rejected votes": 0,
      "NOTA": 29,
      "Total": 662,
      "candidate_votes": [
        190,
        392,
        15,
        5,
        1,
        7,
        2,
        3,
        7,
        11
      ]
    },
    {
      "Serial No. Of Polling Station": 237,
      "Total Number of valid votes": 689,
      "Number of Rejected votes": 0,
      "NOTA": 41,
      "Total": 730,
      "candidate_votes": [
        205,
        388,
        26,
        2,
        6,
        9,
        3,
        5,
        24,
        21
      ]
    },
    {
      "Serial No. Of Polling Station": 238,
      "Total Number of valid votes": 452,
      "Number of Rejected votes": 0,
      "NOTA": 16,
      "Total": 468,
      "candidate_votes": [
        194,
        195,
        27,
        4,
        3,
        6,
        4,
        3,
        11,
        5
      ]
    },
    {
      "Serial No. Of Polling Station": 239,
      "Total Number of valid votes": 559,
      "Number of Rejected votes": 0,
      "NOTA": 16,
      "Total": 575,
      "candidate_votes": [
        109,
        396,
        11,
        5,
        5,
        4,
        6,
        7,
        10,
        6
      ]
    },
    {
      "Serial No. Of Polling Station": 240,
      "Total Number of valid votes": 701,
      "Number of Rejected votes": 0,
      "NOTA": 13,
      "Total": 714,
      "candidate_votes": [
        53,
        579,
        45,
        3,
        4,
        2,
        2,
        5,
        7,
        1
      ]
    },
    {
      "Serial No. Of Polling Station": 241,
      "Total Number of valid votes": 427,
      "Number of Rejected votes": 0,
      "NOTA": 22,
      "Total": 449,
      "candidate_votes": [
        33,
        356,
        10,
        1,
        1,
        1,
        4,
        4,
        9,
        8
      ]
    },
    {
      "Serial No. Of Polling Station": 242,
      "Total Number of valid votes": 522,
      "Number of Rejected votes": 0,
      "NOTA": 15,
      "Total": 537,
      "candidate_votes": [
        60,
        400,
        21,
        4,
        1,
        11,
        5,
        3,
        7,
        10
      ]
    },
    {
      "Serial No. Of Polling Station": 243,
      "Total Number of valid votes": 268,
      "Number of Rejected votes": 0,
      "NOTA": 11,
      "Total": 279,
      "candidate_votes": [
        23,
        222,
        9,
        1,
        4,
        1,
        1,
        1,
        2,
        4
      ]
    },
    {
      "Serial No. Of Polling Station": 244,
      "Total Number of valid votes": 706,
      "Number of Rejected votes": 0,
      "NOTA": 4,
      "Total": 710,
      "candidate_votes": [
        138,
        501,
        25,
        2,
        32,
        1,
        1,
        2,
        1,
        3
      ]
    },
    {
      "Serial No. Of Polling Station": 245,
      "Total Number of valid votes": 491,
      "Number of Rejected votes": 0,
      "NOTA": 7,
      "Total": 498,
      "candidate_votes": [
        50,
        370,
        49,
        1,
        1,
        5,
        6,
        3,
        5,
        1
      ]
    },
    {
      "Serial No. Of Polling Station": 246,
      "Total Number of valid votes": 789,
      "Number of Rejected votes": 0,
      "NOTA": 17,
      "Total": 806,
      "candidate_votes": [
        445,
        311,
        9,
        5,
        2,
        4,
        0,
        5,
        2,
        6
      ]
    },
    {
      "Serial No. Of Polling Station": 247,
      "Total Number of valid votes": 460,
      "Number of Rejected votes": 0,
      "NOTA": 6,
      "Total": 466,
      "candidate_votes": [
        117,
        253,
        62,
        3,
        2,
        5,
        4,
        4,
        7,
        3
      ]
    },
    {
      "Serial No. Of Polling Station": 248,
      "Total Number of valid votes": 712,
      "Number of Rejected votes": 0,
      "NOTA": 14,
      "Total": 726,
      "candidate_votes": [
        366,
        314,
        9,
        6,
        4,
        3,
        3,
        1,
        2,
        4
      ]
    },
    {
      "Serial No. Of Polling Station": 249,
      "Total Number of valid votes": 861,
      "Number of Rejected votes": 0,
      "NOTA": 15,
      "Total": 876,
      "candidate_votes": [
        477,
        331,
        5,
        6,
        4,
        8,
        6,
        6,
        12,
        6
      ]
    },
    {
      "Serial No. Of Polling Station": 250,
      "Total Number of valid votes": 593,
      "Number of Rejected votes": 0,
      "NOTA": 6,
      "Total": 599,
      "candidate_votes": [
        345,
        228,
        9,
        0,
        2,
        0,
        2,
        1,
        5,
        1
      ]
    },
    {
      "Serial No. Of Polling Station": 251,
      "Total Number of valid votes": 668,
      "Number of Rejected votes": 0,
      "NOTA": 8,
      "Total": 676,
      "candidate_votes": [
        207,
        438,
        5,
        0,
        1,
        2,
        3,
        6,
        3,
        3
      ]
    },
    {
      "Serial No. Of Polling Station": 252,
      "Total Number of valid votes": 526,
      "Number of Rejected votes": 0,
      "NOTA": 9,
      "Total": 535,
      "candidate_votes": [
        146,
        369,
        2,
        0,
        1,
        2,
        1,
        1,
        1,
        3
      ]
    },
    {
      "Serial No. Of Polling Station": 253,
      "Total Number of valid votes": 492,
      "Number of Rejected votes": 0,
      "NOTA": 12,
      "Total": 504,
      "candidate_votes": [
        141,
        328,
        6,
        1,
        2,
        2,
        1,
        1,
        4,
        6
      ]
    },
    {
      "Serial No. Of Polling Station": 254,
      "Total Number of valid votes": 692,
      "Number of Rejected votes": 0,
      "NOTA": 17,
      "Total": 709,
      "candidate_votes": [
        448,
        199,
        8,
        3,
        3,
        4,
        5,
        5,
        8,
        9
      ]
    },
    {
      "Serial No. Of Polling Station": 255,
      "Total Number of valid votes": 451,
      "Number of Rejected votes": 0,
      "NOTA": 13,
      "Total": 464,
      "candidate_votes": [
        161,
        255,
        9,
        0,
        3,
        3,
        4,
        7,
        6,
        3
      ]
    },
    {
      "Serial No. Of Polling Station": 256,
      "Total Number of valid votes": 656,
      "Number of Rejected votes": 0,
      "NOTA": 7,
      "Total": 663,
      "candidate_votes": [
        437,
        195,
        5,
        2,
        0,
        4,
        4,
        1,
        5,
        3
      ]
    },
    {
      "Serial No. Of Polling Station": 257,
      "Total Number of valid votes": 463,
      "Number of Rejected votes": 0,
      "NOTA": 3,
      "Total": 466,
      "candidate_votes": [
        306,
        153,
        0,
        0,
        0,
        1,
        1,
        0,
        1,
        1
      ]
    },
    {
      "Serial No. Of Polling Station": 258,
      "Total Number of valid votes": 731,
      "Number of Rejected votes": 0,
      "NOTA": 6,
      "Total": 737,
      "candidate_votes": [
        390,
        330,
        2,
        2,
        0,
        1,
        0,
        3,
        2,
        1
      ]
    },
    {
      "Serial No. Of Polling Station": 259,
      "Total Number of valid votes": 594,
      "Number of Rejected votes": 0,
      "NOTA": 4,
      "Total": 598,
      "candidate_votes": [
        371,
        214,
        1,
        0,
        1,
        1,
        2,
        0,
        2,
        2
      ]
    },
    {
      "Serial No. Of Polling Station": 260,
      "Total Number of valid votes": 607,
      "Number of Rejected votes": 0,
      "NOTA": 14,
      "Total": 621,
      "candidate_votes": [
        366,
        221,
        3,
        1,
        1,
        2,
        1,
        4,
        4,
        4
      ]
    },
    {
      "Serial No. Of Polling Station": 261,
      "Total Number of valid votes": 783,
      "Number of Rejected votes": 0,
      "NOTA": 9,
      "Total": 792,
      "candidate_votes": [
        517,
        215,
        6,
        2,
        4,
        6,
        7,
        4,
        16,
        6
      ]
    },
    {
      "Serial No. Of Polling Station": 262,
      "Total Number of valid votes": 390,
      "Number of Rejected votes": 0,
      "NOTA": 12,
      "Total": 402,
      "candidate_votes": [
        301,
        72,
        2,
        1,
        0,
        0,
        2,
        4,
        6,
        2
      ]
    },
    {
      "Serial No. Of Polling Station": 263,
      "Total Number of valid votes": 863,
      "Number of Rejected votes": 0,
      "NOTA": 7,
      "Total": 870,
      "candidate_votes": [
        717,
        115,
        13,
        5,
        1,
        4,
        2,
        3,
        1,
        2
      ]
    },
    {
      "Serial No. Of Polling Station": 264,
      "Total Number of valid votes": 810,
      "Number of Rejected votes": 0,
      "NOTA": 7,
      "Total": 817,
      "candidate_votes": [
        634,
        136,
        15,
        2,
        4,
        4,
        5,
        2,
        3,
        5
      ]
    },
    {
      "Serial No. Of Polling Station": 265,
      "Total Number of valid votes": 380,
      "Number of Rejected votes": 0,
      "NOTA": 2,
      "Total": 382,
      "candidate_votes": [
        212,
        143,
        11,
        3,
        1,
        3,
        4,
        1,
        0,
        2
      ]
    },
    {
      "Serial No. Of Polling Station": 266,
      "Total Number of valid votes": 371,
      "Number of Rejected votes": 0,
      "NOTA": 5,
      "Total": 376,
      "candidate_votes": [
        65,
        294,
        5,
        0,
        0,
        2,
        1,
        0,
        3,
        1
      ]
    },
    {
      "Serial No. Of Polling Station": 267,
      "Total Number of valid votes": 736,
      "Number of Rejected votes": 0,
      "NOTA": 18,
      "Total": 754,
      "candidate_votes": [
        442,
        252,
        15,
        3,
        1,
        4,
        3,
        5,
        6,
        5
      ]
    },
    {
      "Serial No. Of Polling Station": 268,
      "Total Number of valid votes": 459,
      "Number of Rejected votes": 0,
      "NOTA": 9,
      "Total": 468,
      "candidate_votes": [
        245,
        182,
        4,
        2,
        4,
        1,
        7,
        3,
        4,
        7
      ]
    },
    {
      "Serial No. Of Polling Station": 269,
      "Total Number of valid votes": 150,
      "Number of Rejected votes": 0,
      "NOTA": 4,
      "Total": 154,
      "candidate_votes": [
        66,
        74,
        1,
        0,
        1,
        0,
        2,
        2,
        1,
        3
      ]
    },
    {
      "Serial No. Of Polling Station": 270,
      "Total Number of valid votes": 156,
      "Number of Rejected votes": 0,
      "NOTA": 3,
      "Total": 159,
      "candidate_votes": [
        54,
        93,
        3,
        0,
        0,
        0,
        2,
        1,
        1,
        2
      ]
    }
  ],
  "candidates": [
    {
      "candidate_name": "ASHOK MAHADEORAO NETE"
    },
    {
      "candidate_name": "DR. KIRSAN NAMDEO NAMDEO"
    },
    {
      "candidate_name": "GONNADE YOGESH NAMDEORAO"
    },
    {
      "candidate_name": "DHIRAJ PURUSHOTTAM SHEDMAKE"
    },
    {
      "candidate_name": "BARIKRAO DHARMAJI MADAVI"
    },
    {
      "candidate_name": "SUHAS UMESH KUMRE"
    },
    {
      "candidate_name": "HITESH PANDURANG MADAVI"
    },
    {
      "candidate_name": "KARAN SURESH SAYAM"
    },
    {
      "candidate_name": "KODAPE VILAS SHAMARAO"
    },
    {
      "candidate_name": "VINOD GURUDAS MADAVI"
    }
  ],
  "candidate_names": [
    "ASHOK MAHADEORAO NETE",
    "DR. KIRSAN NAMDEO NAMDEO",
    "GONNADE YOGESH NAMDEORAO",
    "DHIRAJ PURUSHOTTAM SHEDMAKE",
    "BARIKRAO DHARMAJI MADAVI",
    "SUHAS UMESH KUMRE",
    "HITESH PANDURANG MADAVI",
    "KARAN SURESH SAYAM",
    "KODAPE VILAS SHAMARAO",
    "VINOD GURUDAS MADAVI"
  ],
  "extraction_method": "gemini_vision_ultrafast",
  "api_model": "gemini-2.0-flash",
  "pages_available": 12,
  "pages_processed": 10,
  "pages_skipped": 2,
  "parallel_workers": 15,
  "dpi": 120
}